README.rst
setup.py
irmacl/__init__.py
irmacl/apiclient.py
irmacl/bench.py
irmacl/helpers.py
irmacl.egg-info/PKG-INFO
irmacl.egg-info/SOURCES.txt
irmacl.egg-info/dependency_links.txt
irmacl.egg-info/not-zip-safe
irmacl.egg-info/requires.txt
irmacl.egg-info/top_level.txt