Metadata-Version: 1.0
Name: irmacl
Version: 2.0.7
Summary: Irma command line tool for API v2
Home-page: https://github.com/quarkslab/irma-cli
Author: irma-dev
Author-email: irma-dev@quarkslab.com
License: ApacheV2
Platform: UNKNOWN
